LICENSE
MANIFEST.in
README.rst
setup.py
chandl/__init__.py
chandl/__main__.py
chandl/downloader.py
chandl/util.py
chandl.egg-info/PKG-INFO
chandl.egg-info/SOURCES.txt
chandl.egg-info/dependency_links.txt
chandl.egg-info/entry_points.txt
chandl.egg-info/requires.txt
chandl.egg-info/top_level.txt
chandl/model/__init__.py
chandl/model/file.py
chandl/model/post.py
chandl/model/thread.py
chandl/tests/__init__.py
chandl/tests/test_util.py
chandl/tests/model/__init__.py
chandl/tests/model/test_file.py
chandl/tests/model/test_post.py
chandl/tests/model/test_thread.py